pykaldi-0.2.1.dist-info/top_level.txt
pykaldi-0.2.1.dist-info/RECORD
pykaldi-0.2.1.dist-info/METADATA
pykaldi-0.2.1.dist-info/WHEEL
pykaldi-0.2.1.dist-info/LICENSE
kaldi/alignment.py
kaldi/__init__.py
kaldi/asr.py
kaldi/__version__.py
kaldi/segmentation.py
kaldi/ivector/_ivector_extractor.so
kaldi/ivector/__init__.py
kaldi/ivector/_voice_activity_detection.so
kaldi/ivector/_plda.so
kaldi/ivector/_logistic_regression.so
kaldi/ivector/_agglomerative_clustering.so
kaldi/feat/plp.py
kaldi/feat/_wave_reader.so
kaldi/feat/_pitch_functions.so
kaldi/feat/_feature_mfcc.so
kaldi/feat/_mel_computations.so
kaldi/feat/fbank.py
kaldi/feat/__init__.py
kaldi/feat/_feature_window.so
kaldi/feat/mel.py
kaldi/feat/_feature_spectrogram.so
kaldi/feat/_resample.so
kaldi/feat/_feature_functions.so
kaldi/feat/_feature_fbank.so
kaldi/feat/pitch.py
kaldi/feat/_online_feature.so
kaldi/feat/window.py
kaldi/feat/_feature_plp.so
kaldi/feat/_signal.so
kaldi/feat/online.py
kaldi/feat/signal.py
kaldi/feat/functions.py
kaldi/feat/spectrogram.py
kaldi/feat/mfcc.py
kaldi/feat/wave.py
kaldi/online2/_online_gmm_decodable.so
kaldi/online2/_online_feature_pipeline.so
kaldi/online2/_online_endpoint.so
kaldi/online2/_online_nnet2_feature_pipeline.so
kaldi/online2/__init__.py
kaldi/online2/_online_nnet3_decoding_ext.so
kaldi/online2/_online_ivector.py
kaldi/online2/_online_ivector_feature.so
kaldi/online2/_online_gmm_decoding.so
kaldi/online2/_online_nnet3_decoding.so
kaldi/lib/_clif.so
kaldi/itf/_online_feature_itf.so
kaldi/itf/__init__.py
kaldi/itf/_clusterable_itf.so
kaldi/itf/_options_itf.so
kaldi/itf/_decodable_itf.so
kaldi/itf/_context_dep_itf.so
kaldi/base/_fstream.so
kaldi/base/_kaldi_math.so
kaldi/base/_kaldi_error.so
kaldi/base/_kaldi_math_ext.so
kaldi/base/__init__.py
kaldi/base/_timer.so
kaldi/base/io.py
kaldi/base/_io_funcs_ext.so
kaldi/base/_iostream.so
kaldi/base/_sstream.so
kaldi/base/_io_funcs.so
kaldi/base/math.py
kaldi/lat/_compose_lattice_pruned.so
kaldi/lat/sausages.py
kaldi/lat/_lattice_functions.so
kaldi/lat/_phone_align_lattice.so
kaldi/lat/_word_align_lattice.so
